setup.cfg
setup.py
python_wallpaper.egg-info/PKG-INFO
python_wallpaper.egg-info/SOURCES.txt
python_wallpaper.egg-info/dependency_links.txt
python_wallpaper.egg-info/entry_points.txt
python_wallpaper.egg-info/top_level.txt
wallpaper/__init__.py
wallpaper/_natives.c
wallpaper/color_scheme.py
wallpaper/djangoview.py
wallpaper/geometry.py
wallpaper/parameters.py
wallpaper/patterns.py