Metadata-Version: 1.1
Name: python-wallpaper
Version: 0.2.7
Summary: python-wallpaper generates pseudorandom abstract wallpapers
Home-page: https://github.com/ondergetekende/python-wallpaper
Author: Koert van der Veer
Author-email: koert@ondergetekende.nl
License: UNKNOWN
Platform: UNKNOWN
Classifier: Intended Audience :: Developers
Classifier: Operating System :: OS Independent
Classifier: Programming Language :: Python
Classifier: Programming Language :: Python :: 3
